pydra/compose/bidsapp/__init__.py
pydra/compose/bidsapp/_version.py
pydra/compose/bidsapp/app.py
pydra/compose/bidsapp/builder.py
pydra/compose/bidsapp/fields.py
pydra/compose/bidsapp/task.py
pydra/compose/bidsapp/tests/test_bids_app.py
pydra_compose_bidsapp-0.2.2.dist-info/METADATA
pydra_compose_bidsapp-0.2.2.dist-info/WHEEL
pydra_compose_bidsapp-0.2.2.dist-info/licenses/LICENSE
pydra_compose_bidsapp-0.2.2.dist-info/RECORD
